csv2googlesheets/__init__.py
csv2googlesheets/gapi_authorization.py
csv2googlesheets/gapi_create_sheet.py
csv2googlesheets/gapi_write_to_sheet.py
csv2googlesheets/parse_cli_args.py
csv2googlesheets/parse_file.py
csv2googlesheets/to_google_sheets.py
csv2googlesheets-1.0.0.dist-info/LICENSE.txt
csv2googlesheets-1.0.0.dist-info/METADATA
csv2googlesheets-1.0.0.dist-info/WHEEL
csv2googlesheets-1.0.0.dist-info/entry_points.txt
csv2googlesheets-1.0.0.dist-info/top_level.txt
csv2googlesheets-1.0.0.dist-info/RECORD
