Metadata-Version: 2.1
Name: csv2googlesheets
Version: 1.0.0
Summary: Export data from CSV into Google sheets
Home-page: https://github.com/alexskrn/csv2googlesheets
Author: AlexSkrn
Author-email: alex.g.skrn@gmail.com
License: MIT
Keywords: csv to Google sheets converter
Platform: UNKNOWN
Classifier: License :: OSI Approved :: MIT License
Classifier: Programming Language :: Python :: 3
Classifier: Programming Language :: Python :: 3.6
Requires-Python: >=3.6.0,<4.0.0
Requires-Dist: google-api-python-client (<2.0.0,>=1.11.0)
Requires-Dist: google-auth-httplib2 (<1.0.0,>=0.0.4)
Requires-Dist: google-auth-oauthlib (<1.0.0,>=0.4.1)
